{
  "collapse-filter": false,
  "search": "",
  "showTags": false,
  "showAttachments": true,
  "hideUnresolved": true,
  "showOrphans": true,
  "collapse-color-groups": false,
  "colorGroups": [
    {
      "query": "path:00科研相关  ",
      "color": {
        "a": 1,
        "rgb": 14343460
      }
    },
    {
      "query": "path:01生活方面  ",
      "color": {
        "a": 1,
        "rgb": 13438227
      }
    },
    {
      "query": "path:02专业知识  ",
      "color": {
        "a": 1,
        "rgb": 3482828
      }
    },
    {
      "query": "path:03软件网络  ",
      "color": {
        "a": 1,
        "rgb": 64287
      }
    },
    {
      "query": "path:04方法思维  ",
      "color": {
        "a": 1,
        "rgb": 9702862
      }
    },
    {
      "query": "path:05工作职场  ",
      "color": {
        "a": 1,
        "rgb": 16287000
      }
    },
    {
      "query": "path:06口才社交  ",
      "color": {
        "a": 1,
        "rgb": 14505581
      }
    },
    {
      "query": "path:07文学历史  ",
      "color": {
        "a": 1,
        "rgb": 1754565
      }
    },
    {
      "query": "path:08灵感梦想  ",
      "color": {
        "a": 1,
        "rgb": 9524009
      }
    },
    {
      "query": "path:09心灵慰藉  ",
      "color": {
        "a": 1,
        "rgb": 14795039
      }
    },
    {
      "query": "path:10总结反思  ",
      "color": {
        "a": 1,
        "rgb": 14725458
      }
    },
    {
      "query": "path:11情感婚恋  ",
      "color": {
        "a": 1,
        "rgb": 16751081
      }
    },
    {
      "query": "path:12亲子教育  ",
      "color": {
        "a": 1,
        "rgb": 8245504
      }
    },
    {
      "query": "path:00写作运营  ",
      "color": {
        "a": 1,
        "rgb": 6750156
      }
    },
    {
      "query": "path:13英语相关 ",
      "color": {
        "a": 1,
        "rgb": 6119888
      }
    }
  ],
  "collapse-display": false,
  "showArrow": true,
  "textFadeMultiplier": -1.6,
  "nodeSizeMultiplier": 1.03840182323196,
  "lineSizeMultiplier": 0.458051420838972,
  "collapse-forces": false,
  "centerStrength": 0.743186686439282,
  "repelStrength": 16.5088152908222,
  "linkStrength": 0.86290150274197,
  "linkDistance": 320,
  "scale": 1.0956436345690805,
  "close": true
}